speedybottinker/__init__.py
speedybottinker/cards.py
speedybottinker/cli.py
speedybottinker/constants.py
speedybottinker/speedybot.py
speedybottinker-0.1.8.dist-info/METADATA
speedybottinker-0.1.8.dist-info/WHEEL
speedybottinker-0.1.8.dist-info/entry_points.txt
speedybottinker-0.1.8.dist-info/top_level.txt
speedybottinker-0.1.8.dist-info/RECORD
