Metadata-Version: 2.1
Name: speedybottinker
Version: 0.1.8
Summary: Use googles-- highly experimental conversation design infra
Home-page: https://github.com/valgaze/speedybot-loco
Author: Victor Algaze
Author-email: valgaze@gmail.com
Classifier: Programming Language :: Python :: 3
Classifier: License :: OSI Approved :: MIT License
Classifier: Operating System :: OS Independent
Requires-Python: >=3.6
